{
    "string":[
        {
            "name":"group_label_notification",
            "value":"%s ilovasining sizga bildirishnomalar yuborishiga ruxsat berasizmi?",
            "attr":{
                "priority":"LT"
            }
        },
        {
            "name":"ALLOW",
            "value":"Ruxsat",
            "attr":{
                "priority":"LT"
            }
        },
        {
            "name":"BAN",
            "value":"Taqiqlash",
            "attr":{
                "priority":"LT"
            }
        }
    ]
}