{
    "string":[
        {
            "name":"group_label_notification",
            "value":"Разрешить приложению %s отправлять вам уведомления?",
            "attr":{
                "priority":"translate"
            }
        },
        {
            "name":"ALLOW",
            "value":"Разрешить",
            "attr":{
                "priority":"translate"
            }
        },
        {
            "name":"BAN",
            "value":"Запретить",
            "attr":{
                "priority":"translate"
            }
        }
    ]
}