{
    "string":[
        {
            "name":"group_label_notification",
            "value":"Payagan ang %s na magpadala sa iyo ng mga notification?",
            "attr":{
                "priority":"LT"
            }
        },
        {
            "name":"ALLOW",
            "value":"Payagan",
            "attr":{
                "priority":"LT"
            }
        },
        {
            "name":"BAN",
            "value":"Tanggihan",
            "attr":{
                "priority":"LT"
            }
        }
    ]
}